neptuneml_toolkit/__init__.py
neptuneml_toolkit/dataloading/__init__.py
neptuneml_toolkit/dataloading/dataloader.py
neptuneml_toolkit/dataloading/metapath.py
neptuneml_toolkit/graphloader/__init__.py
neptuneml_toolkit/graphloader/graphloader.py
neptuneml_toolkit/metrics/__init__.py
neptuneml_toolkit/metrics/metrics.py
neptuneml_toolkit/modelzoo/__init__.py
neptuneml_toolkit/modelzoo/label_propagation.py
neptuneml_toolkit/modelzoo/mlp.py
neptuneml_toolkit/modelzoo/decoder/__init__.py
neptuneml_toolkit/modelzoo/decoder/distmult.py
neptuneml_toolkit/modelzoo/decoder/dotproduct.py
neptuneml_toolkit/modelzoo/encoder/__init__.py
neptuneml_toolkit/modelzoo/encoder/han.py
neptuneml_toolkit/modelzoo/encoder/rgat.py
neptuneml_toolkit/modelzoo/encoder/rgcn.py
neptuneml_toolkit/modelzoo/feature_generator/__init__.py
neptuneml_toolkit/modelzoo/feature_generator/node_embedding.py
neptuneml_toolkit/modelzoo/feature_transformer/__init__.py
neptuneml_toolkit/modelzoo/feature_transformer/mlp.py
neptuneml_toolkit/train/__init__.py
neptuneml_toolkit/train/train_utils.py
neptuneml_toolkit/transform/__init__.py
neptuneml_toolkit/transform/transform_utils.py
neptuneml_toolkit/utils/__init__.py
neptuneml_toolkit/utils/utils.py
neptuneml_toolkit-0.0.1.dist-info/METADATA
neptuneml_toolkit-0.0.1.dist-info/WHEEL
neptuneml_toolkit-0.0.1.dist-info/top_level.txt
neptuneml_toolkit-0.0.1.dist-info/RECORD
