Metadata-Version: 2.1
Name: neptuneml-toolkit
Version: 0.0.1
Summary: Open source library for training models with Amazon Neptune ML
Home-page: UNKNOWN
Maintainer: Neptune ML Team
Maintainer-email: sojiadeshina@gmail.com
License: Apache 2.0
Platform: UNKNOWN
Classifier: Development Status :: 3 - Alpha
Classifier: Intended Audience :: Developers
Classifier: Natural Language :: English
Classifier: Programming Language :: Python :: 3
Classifier: License :: OSI Approved :: Apache Software License
